{
	"configurations" : 
	[
		{
			"directories" : 
			[
				{
					"build" : ".",
					"jsonFile" : "directory-.-Debug-d0094a50bb2071803777.json",
					"minimumCMakeVersion" : 
					{
						"string" : "3.21"
					},
					"projectIndex" : 0,
					"source" : ".",
					"targetIndexes" : 
					[
						0
					]
				}
			],
			"name" : "Debug",
			"projects" : 
			[
				{
					"directoryIndexes" : 
					[
						0
					],
					"name" : "FullBinaryTree",
					"targetIndexes" : 
					[
						0
					]
				}
			],
			"targets" : 
			[
				{
					"directoryIndex" : 0,
					"id" : "FullBinaryTree::@6890427a1f51a3e7e1df",
					"jsonFile" : "target-FullBinaryTree-Debug-2c74a6c3b1f1a9e2a0d6.json",
					"name" : "FullBinaryTree",
					"projectIndex" : 0
				}
			]
		}
	],
	"kind" : "codemodel",
	"paths" : 
	{
		"build" : "C:/Re-Ki/CPP/Zoom/FullBinaryTree/cmake-build-debug",
		"source" : "C:/Re-Ki/CPP/Zoom/FullBinaryTree"
	},
	"version" : 
	{
		"major" : 2,
		"minor" : 3
	}
}
